terminal_notifier/__init__.py
terminal_notifier/notifier.py
terminal_notifier/sound.mp3
terminal_notifier-0.8.dist-info/METADATA
terminal_notifier-0.8.dist-info/WHEEL
terminal_notifier-0.8.dist-info/top_level.txt
terminal_notifier-0.8.dist-info/RECORD
