Metadata-Version: 2.1
Name: terminal_notifier
Version: 0.8
Summary: A package for notifying users about command execution in the terminal
Author: Anish Tipnis
Requires-Python: >=3.6
Requires-Dist: plyer
Requires-Dist: playsound
